nws_alerts/__init__.py
nws_alerts/subscriptions.py
nws_alerts-1.0.1.dist-info/METADATA
nws_alerts-1.0.1.dist-info/WHEEL
nws_alerts-1.0.1.dist-info/top_level.txt
nws_alerts-1.0.1.dist-info/RECORD
