Metadata-Version: 2.1
Name: nws-alerts
Version: 1.0.1
Summary: Subscribe to alerts from the National Weather Service
Home-page: https://github.com/GrantGMiller/nws_alerts
Author: Grant miller
Author-email: grant@grant-miller.com
License: PSF
Project-URL: Source Code, https://github.com/GrantGMiller/nws_alerts
Keywords: grant miller national weather service nws alert common alert protocol cap
Platform: UNKNOWN
Requires-Dist: nwscapparser3
